<?xml version="1.0" encoding="utf-8"?><soap:Envelope xmlns:soap="http://www.w3.org/2003/05/soap-envelope" xmlns:xsi="http://www.w3.org/2001/XMLSchema-instance" xmlns:xsd="http://www.w3.org/2001/XMLSchema"><soap:Body><getDomesticCityResponse xmlns="http://WebXml.com.cn/"><getDomesticCityResult><xs:schema id="Airline1" xmlns="" xmlns:xs="http://www.w3.org/2001/XMLSchema" xmlns:msdata="urn:schemas-microsoft-com:xml-msdata"><xs:element name="Airline1" msdata:IsDataSet="true" msdata:UseCurrentLocale="true"><xs:complexType><xs:choice minOccurs="0" maxOccurs="unbounded"><xs:element name="Address"><xs:complexType><xs:sequence><xs:element name="enCityName" type="xs:string" minOccurs="0" /><xs:element name="cnCityName" type="xs:string" minOccurs="0" /><xs:element name="Abbreviation" type="xs:string" minOccurs="0" /></xs:sequence></xs:complexType></xs:element></xs:choice></xs:complexType></xs:element></xs:schema><diffgr:diffgram xmlns:msdata="urn:schemas-microsoft-com:xml-msdata" xmlns:diffgr="urn:schemas-microsoft-com:xml-diffgram-v1"><Airline1 xmlns=""><Address diffgr:id="Address1" msdata:rowOrder="0"><enCityName>Aershan</enCityName><cnCityName>阿尔山</cnCityName><Abbreviation>YIE</Abbreviation></Address><Address diffgr:id="Address2" msdata:rowOrder="1"><enCityName>Akesu</enCityName><cnCityName>阿克苏</cnCityName><Abbreviation>AKU</Abbreviation></Address><Address diffgr:id="Address3" msdata:rowOrder="2"><enCityName>Aletai</enCityName><cnCityName>阿勒泰</cnCityName><Abbreviation>AAT</Abbreviation></Address><Address diffgr:id="Address4" msdata:rowOrder="3"><enCityName>Ali</enCityName><cnCityName>阿里</cnCityName><Abbreviation>NGQ</Abbreviation></Address><Address diffgr:id="Address5" msdata:rowOrder="4"><enCityName>Ankang</enCityName><cnCityName>安康</cnCityName><Abbreviation>AKA</Abbreviation></Address><Address diffgr:id="Address6" msdata:rowOrder="5"><enCityName>Anqing</enCityName><cnCityName>安庆</cnCityName><Abbreviation>AQG</Abbreviation></Address><Address diffgr:id="Address7" msdata:rowOrder="6"><enCityName>Anshan</enCityName><cnCityName>鞍山</cnCityName><Abbreviation>AOG</Abbreviation></Address><Address diffgr:id="Address8" msdata:rowOrder="7"><enCityName>Anshun</enCityName><cnCityName>安顺</cnCityName><Abbreviation>AVA</Abbreviation></Address><Address diffgr:id="Address9" msdata:rowOrder="8"><enCityName>Anyang</enCityName><cnCityName>安阳</cnCityName><Abbreviation>AYN</Abbreviation></Address><Address diffgr:id="Address10" msdata:rowOrder="9"><enCityName>Baise</enCityName><cnCityName>百色</cnCityName><Abbreviation>AEB</Abbreviation></Address><Address diffgr:id="Address11" msdata:rowOrder="10"><enCityName>Baoshan</enCityName><cnCityName>保山</cnCityName><Abbreviation>BSD</Abbreviation></Address><Address diffgr:id="Address12" msdata:rowOrder="11"><enCityName>Baotou</enCityName><cnCityName>包头</cnCityName><Abbreviation>BAV</Abbreviation></Address><Address diffgr:id="Address13" msdata:rowOrder="12"><enCityName>Bayannaoer</enCityName><cnCityName>巴彦淖尔</cnCityName><Abbreviation>RLK</Abbreviation></Address><Address diffgr:id="Address14" msdata:rowOrder="13"><enCityName>Beihai</enCityName><cnCityName>北海</cnCityName><Abbreviation>BHY</Abbreviation></Address><Address diffgr:id="Address15" msdata:rowOrder="14"><enCityName>Beijing</enCityName><cnCityName>北京</cnCityName><Abbreviation>BJS</Abbreviation></Address><Address diffgr:id="Address16" msdata:rowOrder="15"><enCityName>Bengbu</enCityName><cnCityName>蚌埠</cnCityName><Abbreviation>BFU</Abbreviation></Address><Address diffgr:id="Address17" msdata:rowOrder="16"><enCityName>bijie</enCityName><cnCityName>毕节</cnCityName><Abbreviation>BFJ</Abbreviation></Address><Address diffgr:id="Address18" msdata:rowOrder="17"><enCityName>Bole</enCityName><cnCityName>博乐</cnCityName><Abbreviation>BPL</Abbreviation></Address><Address diffgr:id="Address19" msdata:rowOrder="18"><enCityName>Changbaishan</enCityName><cnCityName>长白山</cnCityName><Abbreviation>NBS</Abbreviation></Address><Address diffgr:id="Address20" msdata:rowOrder="19"><enCityName>Changchun</enCityName><cnCityName>长春</cnCityName><Abbreviation>CGQ</Abbreviation></Address><Address diffgr:id="Address21" msdata:rowOrder="20"><enCityName>Changde</enCityName><cnCityName>常德</cnCityName><Abbreviation>CGD</Abbreviation></Address><Address diffgr:id="Address22" msdata:rowOrder="21"><enCityName>Changdu</enCityName><cnCityName>昌都</cnCityName><Abbreviation>BPX</Abbreviation></Address><Address diffgr:id="Address23" msdata:rowOrder="22"><enCityName>Changsha</enCityName><cnCityName>长沙</cnCityName><Abbreviation>CSX</Abbreviation></Address><Address diffgr:id="Address24" msdata:rowOrder="23"><enCityName>Changzhi</enCityName><cnCityName>长治</cnCityName><Abbreviation>CIH</Abbreviation></Address><Address diffgr:id="Address25" msdata:rowOrder="24"><enCityName>Changzhou</enCityName><cnCityName>常州</cnCityName><Abbreviation>CZX</Abbreviation></Address><Address diffgr:id="Address26" msdata:rowOrder="25"><enCityName>Chaoyang</enCityName><cnCityName>朝阳</cnCityName><Abbreviation>CHG</Abbreviation></Address><Address diffgr:id="Address27" msdata:rowOrder="26"><enCityName>Chengdu</enCityName><cnCityName>成都</cnCityName><Abbreviation>CTU</Abbreviation></Address><Address diffgr:id="Address28" msdata:rowOrder="27"><enCityName>CHIAYI</enCityName><cnCityName>嘉义</cnCityName><Abbreviation>CYI</Abbreviation></Address><Address diffgr:id="Address29" msdata:rowOrder="28"><enCityName>Chifeng</enCityName><cnCityName>赤峰</cnCityName><Abbreviation>CIF</Abbreviation></Address><Address diffgr:id="Address30" msdata:rowOrder="29"><enCityName>Chongqing</enCityName><cnCityName>重庆</cnCityName><Abbreviation>CKG</Abbreviation></Address><Address diffgr:id="Address31" msdata:rowOrder="30"><enCityName>dali</enCityName><cnCityName>大理</cnCityName><Abbreviation>DLU</Abbreviation></Address><Address diffgr:id="Address32" msdata:rowOrder="31"><enCityName>Dali</enCityName><cnCityName>大理市</cnCityName><Abbreviation>DLU</Abbreviation></Address><Address diffgr:id="Address33" msdata:rowOrder="32"><enCityName>Dalian</enCityName><cnCityName>大连</cnCityName><Abbreviation>DLC</Abbreviation></Address><Address diffgr:id="Address34" msdata:rowOrder="33"><enCityName>Dandong</enCityName><cnCityName>丹东</cnCityName><Abbreviation>DDG</Abbreviation></Address><Address diffgr:id="Address35" msdata:rowOrder="34"><enCityName>Daqing</enCityName><cnCityName>大庆</cnCityName><Abbreviation>DQA</Abbreviation></Address><Address diffgr:id="Address36" msdata:rowOrder="35"><enCityName>Datong</enCityName><cnCityName>大同</cnCityName><Abbreviation>DAT</Abbreviation></Address><Address diffgr:id="Address37" msdata:rowOrder="36"><enCityName>Daxian</enCityName><cnCityName>达县</cnCityName><Abbreviation>DAX</Abbreviation></Address><Address diffgr:id="Address38" msdata:rowOrder="37"><enCityName>Dazhou</enCityName><cnCityName>达州</cnCityName><Abbreviation>DAX</Abbreviation></Address><Address diffgr:id="Address39" msdata:rowOrder="38"><enCityName>Dehong</enCityName><cnCityName>德宏</cnCityName><Abbreviation>LUM</Abbreviation></Address><Address diffgr:id="Address40" msdata:rowOrder="39"><enCityName>Deyang</enCityName><cnCityName>德阳</cnCityName><Abbreviation>DEY</Abbreviation></Address><Address diffgr:id="Address41" msdata:rowOrder="40"><enCityName>Diqing</enCityName><cnCityName>迪庆</cnCityName><Abbreviation>DIG</Abbreviation></Address><Address diffgr:id="Address42" msdata:rowOrder="41"><enCityName>Dongguan</enCityName><cnCityName>东莞</cnCityName><Abbreviation>DGM</Abbreviation></Address><Address diffgr:id="Address43" msdata:rowOrder="42"><enCityName>Dongying</enCityName><cnCityName>东营</cnCityName><Abbreviation>DOY</Abbreviation></Address><Address diffgr:id="Address44" msdata:rowOrder="43"><enCityName>Dunhuang</enCityName><cnCityName>敦煌</cnCityName><Abbreviation>DNH</Abbreviation></Address><Address diffgr:id="Address45" msdata:rowOrder="44"><enCityName>E'erduosi</enCityName><cnCityName>鄂尔多斯</cnCityName><Abbreviation>DSN</Abbreviation></Address><Address diffgr:id="Address46" msdata:rowOrder="45"><enCityName>ELIANHAOTE</enCityName><cnCityName>二连浩特</cnCityName><Abbreviation>ERL</Abbreviation></Address><Address diffgr:id="Address47" msdata:rowOrder="46"><enCityName>Enshi</enCityName><cnCityName>恩施</cnCityName><Abbreviation>ENH</Abbreviation></Address><Address diffgr:id="Address48" msdata:rowOrder="47"><enCityName>Foshan</enCityName><cnCityName>佛山</cnCityName><Abbreviation>FUO</Abbreviation></Address><Address diffgr:id="Address49" msdata:rowOrder="48"><enCityName>Fuyang</enCityName><cnCityName>阜阳</cnCityName><Abbreviation>FUG</Abbreviation></Address><Address diffgr:id="Address50" msdata:rowOrder="49"><enCityName>Fuyun</enCityName><cnCityName>富蕴</cnCityName><Abbreviation>FYN</Abbreviation></Address><Address diffgr:id="Address51" msdata:rowOrder="50"><enCityName>Fuzhou</enCityName><cnCityName>福州</cnCityName><Abbreviation>FOC</Abbreviation></Address><Address diffgr:id="Address52" msdata:rowOrder="51"><enCityName>Ganzhou</enCityName><cnCityName>赣州</cnCityName><Abbreviation>KOW</Abbreviation></Address><Address diffgr:id="Address53" msdata:rowOrder="52"><enCityName>Ge'ermu</enCityName><cnCityName>格尔木</cnCityName><Abbreviation>GOQ</Abbreviation></Address><Address diffgr:id="Address54" msdata:rowOrder="53"><enCityName>Guanghan</enCityName><cnCityName>广汉</cnCityName><Abbreviation>GHN</Abbreviation></Address><Address diffgr:id="Address55" msdata:rowOrder="54"><enCityName>Guanghua</enCityName><cnCityName>光化</cnCityName><Abbreviation>LHK</Abbreviation></Address><Address diffgr:id="Address56" msdata:rowOrder="55"><enCityName>Guangyuan</enCityName><cnCityName>广元</cnCityName><Abbreviation>GYS</Abbreviation></Address><Address diffgr:id="Address57" msdata:rowOrder="56"><enCityName>Guangzhou</enCityName><cnCityName>广州</cnCityName><Abbreviation>CAN</Abbreviation></Address><Address diffgr:id="Address58" msdata:rowOrder="57"><enCityName>Guilin</enCityName><cnCityName>桂林</cnCityName><Abbreviation>KWL</Abbreviation></Address><Address diffgr:id="Address59" msdata:rowOrder="58"><enCityName>Guiyang</enCityName><cnCityName>贵阳</cnCityName><Abbreviation>KWE</Abbreviation></Address><Address diffgr:id="Address60" msdata:rowOrder="59"><enCityName>Guyuan</enCityName><cnCityName>固原</cnCityName><Abbreviation>GYU</Abbreviation></Address><Address diffgr:id="Address61" msdata:rowOrder="60"><enCityName>Haerbin</enCityName><cnCityName>哈尔滨</cnCityName><Abbreviation>HRB</Abbreviation></Address><Address diffgr:id="Address62" msdata:rowOrder="61"><enCityName>Haikou</enCityName><cnCityName>海口</cnCityName><Abbreviation>HAK</Abbreviation></Address><Address diffgr:id="Address63" msdata:rowOrder="62"><enCityName>Hailaer</enCityName><cnCityName>海拉尔</cnCityName><Abbreviation>HLD</Abbreviation></Address><Address diffgr:id="Address64" msdata:rowOrder="63"><enCityName>Hami</enCityName><cnCityName>哈密市</cnCityName><Abbreviation>HMI</Abbreviation></Address><Address diffgr:id="Address65" msdata:rowOrder="64"><enCityName>hami</enCityName><cnCityName>哈密</cnCityName><Abbreviation>HMI</Abbreviation></Address><Address diffgr:id="Address66" msdata:rowOrder="65"><enCityName>Handan</enCityName><cnCityName>邯郸</cnCityName><Abbreviation>HDG</Abbreviation></Address><Address diffgr:id="Address67" msdata:rowOrder="66"><enCityName>Hangzhou</enCityName><cnCityName>杭州</cnCityName><Abbreviation>HGH</Abbreviation></Address><Address diffgr:id="Address68" msdata:rowOrder="67"><enCityName>Hanzhong</enCityName><cnCityName>汉中</cnCityName><Abbreviation>HZG</Abbreviation></Address><Address diffgr:id="Address69" msdata:rowOrder="68"><enCityName>Hefei</enCityName><cnCityName>合肥</cnCityName><Abbreviation>HFE</Abbreviation></Address><Address diffgr:id="Address70" msdata:rowOrder="69"><enCityName>Heihe</enCityName><cnCityName>黑河</cnCityName><Abbreviation>HEK</Abbreviation></Address><Address diffgr:id="Address71" msdata:rowOrder="70"><enCityName>Hengyang</enCityName><cnCityName>衡阳</cnCityName><Abbreviation>HNY</Abbreviation></Address><Address diffgr:id="Address72" msdata:rowOrder="71"><enCityName>hetian</enCityName><cnCityName>和田</cnCityName><Abbreviation>HTN</Abbreviation></Address><Address diffgr:id="Address73" msdata:rowOrder="72"><enCityName>Hetian</enCityName><cnCityName>和田市</cnCityName><Abbreviation>HTN</Abbreviation></Address><Address diffgr:id="Address74" msdata:rowOrder="73"><enCityName>Hong Kong</enCityName><cnCityName>香港</cnCityName><Abbreviation>HKG</Abbreviation></Address><Address diffgr:id="Address75" msdata:rowOrder="74"><enCityName>Huai'an</enCityName><cnCityName>淮安</cnCityName><Abbreviation>HIA</Abbreviation></Address><Address diffgr:id="Address76" msdata:rowOrder="75"><enCityName>Huaihua</enCityName><cnCityName>怀化</cnCityName><Abbreviation>HJJ</Abbreviation></Address><Address diffgr:id="Address77" msdata:rowOrder="76"><enCityName>HUALIEN</enCityName><cnCityName>花莲</cnCityName><Abbreviation>HUN</Abbreviation></Address><Address diffgr:id="Address78" msdata:rowOrder="77"><enCityName>Huangshan</enCityName><cnCityName>黄山</cnCityName><Abbreviation>TXN</Abbreviation></Address><Address diffgr:id="Address79" msdata:rowOrder="78"><enCityName>Huangshi</enCityName><cnCityName>黄石</cnCityName><Abbreviation>XAA</Abbreviation></Address><Address diffgr:id="Address80" msdata:rowOrder="79"><enCityName>Huangyan</enCityName><cnCityName>黄岩</cnCityName><Abbreviation>HYN</Abbreviation></Address><Address diffgr:id="Address81" msdata:rowOrder="80"><enCityName>Huhehaote</enCityName><cnCityName>呼和浩特</cnCityName><Abbreviation>HET</Abbreviation></Address><Address diffgr:id="Address82" msdata:rowOrder="81"><enCityName>Huizhou</enCityName><cnCityName>惠州</cnCityName><Abbreviation>HUZ</Abbreviation></Address><Address diffgr:id="Address83" msdata:rowOrder="82"><enCityName>Jiagedaqi</enCityName><cnCityName>加格达奇</cnCityName><Abbreviation>JGD</Abbreviation></Address><Address diffgr:id="Address84" msdata:rowOrder="83"><enCityName>Jiamusi</enCityName><cnCityName>佳木斯</cnCityName><Abbreviation>JMU</Abbreviation></Address><Address diffgr:id="Address85" msdata:rowOrder="84"><enCityName>Jian</enCityName><cnCityName>吉安</cnCityName><Abbreviation>KNC</Abbreviation></Address><Address diffgr:id="Address86" msdata:rowOrder="85"><enCityName>Jiayuguan</enCityName><cnCityName>嘉峪关</cnCityName><Abbreviation>JGN</Abbreviation></Address><Address diffgr:id="Address87" msdata:rowOrder="86"><enCityName>Jieyang</enCityName><cnCityName>揭阳</cnCityName><Abbreviation>SWA</Abbreviation></Address><Address diffgr:id="Address88" msdata:rowOrder="87"><enCityName>Jilin</enCityName><cnCityName>吉林</cnCityName><Abbreviation>JIL</Abbreviation></Address><Address diffgr:id="Address89" msdata:rowOrder="88"><enCityName>Jinan</enCityName><cnCityName>济南</cnCityName><Abbreviation>TNA</Abbreviation></Address><Address diffgr:id="Address90" msdata:rowOrder="89"><enCityName>Jinchang</enCityName><cnCityName>金昌</cnCityName><Abbreviation>JIC</Abbreviation></Address><Address diffgr:id="Address91" msdata:rowOrder="90"><enCityName>Jingdezhen</enCityName><cnCityName>景德镇</cnCityName><Abbreviation>JDZ</Abbreviation></Address><Address diffgr:id="Address92" msdata:rowOrder="91"><enCityName>Jinggangshan</enCityName><cnCityName>井冈山</cnCityName><Abbreviation>JGS</Abbreviation></Address><Address diffgr:id="Address93" msdata:rowOrder="92"><enCityName>Jinghong</enCityName><cnCityName>景洪</cnCityName><Abbreviation>JHG</Abbreviation></Address><Address diffgr:id="Address94" msdata:rowOrder="93"><enCityName>Jining</enCityName><cnCityName>济宁</cnCityName><Abbreviation>JNG</Abbreviation></Address><Address diffgr:id="Address95" msdata:rowOrder="94"><enCityName>Jinjiang</enCityName><cnCityName>晋江</cnCityName><Abbreviation>JJN</Abbreviation></Address><Address diffgr:id="Address96" msdata:rowOrder="95"><enCityName>Jinzhou</enCityName><cnCityName>锦州</cnCityName><Abbreviation>JNZ</Abbreviation></Address><Address diffgr:id="Address97" msdata:rowOrder="96"><enCityName>Jiuhuashan</enCityName><cnCityName>九华山</cnCityName><Abbreviation>JUH</Abbreviation></Address><Address diffgr:id="Address98" msdata:rowOrder="97"><enCityName>Jiujiang</enCityName><cnCityName>九江</cnCityName><Abbreviation>JIU</Abbreviation></Address><Address diffgr:id="Address99" msdata:rowOrder="98"><enCityName>Jiuzhaigou</enCityName><cnCityName>九寨沟</cnCityName><Abbreviation>JZH</Abbreviation></Address><Address diffgr:id="Address100" msdata:rowOrder="99"><enCityName>Jixi</enCityName><cnCityName>鸡西</cnCityName><Abbreviation>JXA</Abbreviation></Address><Address diffgr:id="Address101" msdata:rowOrder="100"><enCityName>kanasi</enCityName><cnCityName>喀纳斯</cnCityName><Abbreviation>KJI</Abbreviation></Address><Address diffgr:id="Address102" msdata:rowOrder="101"><enCityName>Kangding</enCityName><cnCityName>康定</cnCityName><Abbreviation>KGT</Abbreviation></Address><Address diffgr:id="Address103" msdata:rowOrder="102"><enCityName>Kaohsiung</enCityName><cnCityName>高雄</cnCityName><Abbreviation>KHH</Abbreviation></Address><Address diffgr:id="Address104" msdata:rowOrder="103"><enCityName>Kashi</enCityName><cnCityName>喀什市</cnCityName><Abbreviation>KHG</Abbreviation></Address><Address diffgr:id="Address105" msdata:rowOrder="104"><enCityName>kashi</enCityName><cnCityName>喀什</cnCityName><Abbreviation>KHG</Abbreviation></Address><Address diffgr:id="Address106" msdata:rowOrder="105"><enCityName>Kelamayi</enCityName><cnCityName>克拉玛依</cnCityName><Abbreviation>KRY</Abbreviation></Address><Address diffgr:id="Address107" msdata:rowOrder="106"><enCityName>KINMEN</enCityName><cnCityName>金门</cnCityName><Abbreviation>KNH</Abbreviation></Address><Address diffgr:id="Address108" msdata:rowOrder="107"><enCityName>Kuche</enCityName><cnCityName>库车</cnCityName><Abbreviation>KCA</Abbreviation></Address><Address diffgr:id="Address109" msdata:rowOrder="108"><enCityName>Kuerle</enCityName><cnCityName>库尔勒</cnCityName><Abbreviation>KRL</Abbreviation></Address><Address diffgr:id="Address110" msdata:rowOrder="109"><enCityName>Kunming</enCityName><cnCityName>昆明</cnCityName><Abbreviation>KMG</Abbreviation></Address><Address diffgr:id="Address111" msdata:rowOrder="110"><enCityName>Lanzhou</enCityName><cnCityName>兰州</cnCityName><Abbreviation>LHW</Abbreviation></Address><Address diffgr:id="Address112" msdata:rowOrder="111"><enCityName>Lasa</enCityName><cnCityName>拉萨</cnCityName><Abbreviation>LXA</Abbreviation></Address><Address diffgr:id="Address113" msdata:rowOrder="112"><enCityName>Liancheng</enCityName><cnCityName>连城</cnCityName><Abbreviation>LCX</Abbreviation></Address><Address diffgr:id="Address114" msdata:rowOrder="113"><enCityName>Liangping</enCityName><cnCityName>梁平</cnCityName><Abbreviation>LIA</Abbreviation></Address><Address diffgr:id="Address115" msdata:rowOrder="114"><enCityName>Lianyungang</enCityName><cnCityName>连云港</cnCityName><Abbreviation>LYG</Abbreviation></Address><Address diffgr:id="Address116" msdata:rowOrder="115"><enCityName>libo</enCityName><cnCityName>荔波</cnCityName><Abbreviation>LLB</Abbreviation></Address><Address diffgr:id="Address117" msdata:rowOrder="116"><enCityName>Lijiang</enCityName><cnCityName>丽江</cnCityName><Abbreviation>LJG</Abbreviation></Address><Address diffgr:id="Address118" msdata:rowOrder="117"><enCityName>Lincang</enCityName><cnCityName>临沧</cnCityName><Abbreviation>LNJ</Abbreviation></Address><Address diffgr:id="Address119" msdata:rowOrder="118"><enCityName>Linxi</enCityName><cnCityName>林西</cnCityName><Abbreviation>LXI</Abbreviation></Address><Address diffgr:id="Address120" msdata:rowOrder="119"><enCityName>Linyi</enCityName><cnCityName>临沂</cnCityName><Abbreviation>LYI</Abbreviation></Address><Address diffgr:id="Address121" msdata:rowOrder="120"><enCityName>Linzhi</enCityName><cnCityName>林芝</cnCityName><Abbreviation>LZY</Abbreviation></Address><Address diffgr:id="Address122" msdata:rowOrder="121"><enCityName>LIPING</enCityName><cnCityName>黎平</cnCityName><Abbreviation>HZH</Abbreviation></Address><Address diffgr:id="Address123" msdata:rowOrder="122"><enCityName>Liuzhou</enCityName><cnCityName>柳州</cnCityName><Abbreviation>LZH</Abbreviation></Address><Address diffgr:id="Address124" msdata:rowOrder="123"><enCityName>Longyan</enCityName><cnCityName>龙岩</cnCityName><Abbreviation>LCX</Abbreviation></Address><Address diffgr:id="Address125" msdata:rowOrder="124"><enCityName>Luoyang</enCityName><cnCityName>洛阳</cnCityName><Abbreviation>LYA</Abbreviation></Address><Address diffgr:id="Address126" msdata:rowOrder="125"><enCityName>Luzhou</enCityName><cnCityName>泸州</cnCityName><Abbreviation>LZO</Abbreviation></Address><Address diffgr:id="Address127" msdata:rowOrder="126"><enCityName>Macau</enCityName><cnCityName>澳门</cnCityName><Abbreviation>MFM</Abbreviation></Address><Address diffgr:id="Address128" msdata:rowOrder="127"><enCityName>MAKUNG</enCityName><cnCityName>马公</cnCityName><Abbreviation>MZG</Abbreviation></Address><Address diffgr:id="Address129" msdata:rowOrder="128"><enCityName>Mangshi</enCityName><cnCityName>芒市</cnCityName><Abbreviation>LUM</Abbreviation></Address><Address diffgr:id="Address130" msdata:rowOrder="129"><enCityName>Manzhouli</enCityName><cnCityName>满洲里</cnCityName><Abbreviation>NZH</Abbreviation></Address><Address diffgr:id="Address131" msdata:rowOrder="130"><enCityName>MEI XIAN</enCityName><cnCityName>梅县</cnCityName><Abbreviation>MXZ</Abbreviation></Address><Address diffgr:id="Address132" msdata:rowOrder="131"><enCityName>Meizhou</enCityName><cnCityName>梅州</cnCityName><Abbreviation>MXZ</Abbreviation></Address><Address diffgr:id="Address133" msdata:rowOrder="132"><enCityName>Mianyang</enCityName><cnCityName>绵阳</cnCityName><Abbreviation>MIG</Abbreviation></Address><Address diffgr:id="Address134" msdata:rowOrder="133"><enCityName>Mohe</enCityName><cnCityName>漠河</cnCityName><Abbreviation>OHE</Abbreviation></Address><Address diffgr:id="Address135" msdata:rowOrder="134"><enCityName>Mudanjiang</enCityName><cnCityName>牡丹江</cnCityName><Abbreviation>MDG</Abbreviation></Address><Address diffgr:id="Address136" msdata:rowOrder="135"><enCityName>Nalati</enCityName><cnCityName>那拉提</cnCityName><Abbreviation>NLT</Abbreviation></Address><Address diffgr:id="Address137" msdata:rowOrder="136"><enCityName>Nanchang</enCityName><cnCityName>南昌</cnCityName><Abbreviation>KHN</Abbreviation></Address><Address diffgr:id="Address138" msdata:rowOrder="137"><enCityName>Nanchong</enCityName><cnCityName>南充</cnCityName><Abbreviation>NAO</Abbreviation></Address><Address diffgr:id="Address139" msdata:rowOrder="138"><enCityName>Nanjing</enCityName><cnCityName>南京</cnCityName><Abbreviation>NKG</Abbreviation></Address><Address diffgr:id="Address140" msdata:rowOrder="139"><enCityName>Nanning</enCityName><cnCityName>南宁</cnCityName><Abbreviation>NNG</Abbreviation></Address><Address diffgr:id="Address141" msdata:rowOrder="140"><enCityName>Nantong</enCityName><cnCityName>南通</cnCityName><Abbreviation>NTG</Abbreviation></Address><Address diffgr:id="Address142" msdata:rowOrder="141"><enCityName>Nanyang</enCityName><cnCityName>南阳</cnCityName><Abbreviation>NNY</Abbreviation></Address><Address diffgr:id="Address143" msdata:rowOrder="142"><enCityName>Ningbo</enCityName><cnCityName>宁波</cnCityName><Abbreviation>NGB</Abbreviation></Address><Address diffgr:id="Address144" msdata:rowOrder="143"><enCityName>Panzhihua</enCityName><cnCityName>攀枝花</cnCityName><Abbreviation>PZI</Abbreviation></Address><Address diffgr:id="Address145" msdata:rowOrder="144"><enCityName>Puer</enCityName><cnCityName>普洱</cnCityName><Abbreviation>SYM</Abbreviation></Address><Address diffgr:id="Address146" msdata:rowOrder="145"><enCityName>Putuoshan</enCityName><cnCityName>普陀山</cnCityName><Abbreviation>HSN</Abbreviation></Address><Address diffgr:id="Address147" msdata:rowOrder="146"><enCityName>Qianjiang</enCityName><cnCityName>黔江</cnCityName><Abbreviation>JIQ</Abbreviation></Address><Address diffgr:id="Address148" msdata:rowOrder="147"><enCityName>Qiemo</enCityName><cnCityName>且末</cnCityName><Abbreviation>IQM</Abbreviation></Address><Address diffgr:id="Address149" msdata:rowOrder="148"><enCityName>Qingdao</enCityName><cnCityName>青岛</cnCityName><Abbreviation>TAO</Abbreviation></Address><Address diffgr:id="Address150" msdata:rowOrder="149"><enCityName>Qingyang</enCityName><cnCityName>庆阳</cnCityName><Abbreviation>IQN</Abbreviation></Address><Address diffgr:id="Address151" msdata:rowOrder="150"><enCityName>Qinhuangdao</enCityName><cnCityName>秦皇岛</cnCityName><Abbreviation>SHP</Abbreviation></Address><Address diffgr:id="Address152" msdata:rowOrder="151"><enCityName>Qiqihaer</enCityName><cnCityName>齐齐哈尔</cnCityName><Abbreviation>NDG</Abbreviation></Address><Address diffgr:id="Address153" msdata:rowOrder="152"><enCityName>Quanzhou</enCityName><cnCityName>泉州</cnCityName><Abbreviation>JJN</Abbreviation></Address><Address diffgr:id="Address154" msdata:rowOrder="153"><enCityName>Quzhou</enCityName><cnCityName>衢州</cnCityName><Abbreviation>JUZ</Abbreviation></Address><Address diffgr:id="Address155" msdata:rowOrder="154"><enCityName>Rikaze</enCityName><cnCityName>日喀则</cnCityName><Abbreviation>RKZ</Abbreviation></Address><Address diffgr:id="Address156" msdata:rowOrder="155"><enCityName>Sanya</enCityName><cnCityName>三亚</cnCityName><Abbreviation>SYX</Abbreviation></Address><Address diffgr:id="Address157" msdata:rowOrder="156"><enCityName>Shanghai</enCityName><cnCityName>上海</cnCityName><Abbreviation>SHA</Abbreviation></Address><Address diffgr:id="Address158" msdata:rowOrder="157"><enCityName>Shanhaiguan</enCityName><cnCityName>山海关</cnCityName><Abbreviation>SHP</Abbreviation></Address><Address diffgr:id="Address159" msdata:rowOrder="158"><enCityName>Shantou</enCityName><cnCityName>汕头</cnCityName><Abbreviation>SWA</Abbreviation></Address><Address diffgr:id="Address160" msdata:rowOrder="159"><enCityName>Shashi</enCityName><cnCityName>沙市</cnCityName><Abbreviation>SHS</Abbreviation></Address><Address diffgr:id="Address161" msdata:rowOrder="160"><enCityName>Shenyang</enCityName><cnCityName>沈阳</cnCityName><Abbreviation>SHE</Abbreviation></Address><Address diffgr:id="Address162" msdata:rowOrder="161"><enCityName>Shenzhen</enCityName><cnCityName>深圳</cnCityName><Abbreviation>SZX</Abbreviation></Address><Address diffgr:id="Address163" msdata:rowOrder="162"><enCityName>Shijiazhuang</enCityName><cnCityName>石家庄</cnCityName><Abbreviation>SJW</Abbreviation></Address><Address diffgr:id="Address164" msdata:rowOrder="163"><enCityName>Shishi</enCityName><cnCityName>石狮</cnCityName><Abbreviation>JJN</Abbreviation></Address><Address diffgr:id="Address165" msdata:rowOrder="164"><enCityName>Simao</enCityName><cnCityName>思茅</cnCityName><Abbreviation>SYM</Abbreviation></Address><Address diffgr:id="Address166" msdata:rowOrder="165"><enCityName>Suzhou</enCityName><cnCityName>苏州</cnCityName><Abbreviation>SZV</Abbreviation></Address><Address diffgr:id="Address167" msdata:rowOrder="166"><enCityName>Tacheng</enCityName><cnCityName>塔城</cnCityName><Abbreviation>TCG</Abbreviation></Address><Address diffgr:id="Address168" msdata:rowOrder="167"><enCityName>Taichung</enCityName><cnCityName>台中</cnCityName><Abbreviation>TXG</Abbreviation></Address><Address diffgr:id="Address169" msdata:rowOrder="168"><enCityName>Taipei</enCityName><cnCityName>台北</cnCityName><Abbreviation>TPE</Abbreviation></Address><Address diffgr:id="Address170" msdata:rowOrder="169"><enCityName>Taitung</enCityName><cnCityName>台东</cnCityName><Abbreviation>TTT</Abbreviation></Address><Address diffgr:id="Address171" msdata:rowOrder="170"><enCityName>Taiyuan</enCityName><cnCityName>太原</cnCityName><Abbreviation>TYN</Abbreviation></Address><Address diffgr:id="Address172" msdata:rowOrder="171"><enCityName>Taizhou</enCityName><cnCityName>台州</cnCityName><Abbreviation>HYN</Abbreviation></Address><Address diffgr:id="Address173" msdata:rowOrder="172"><enCityName>Tangshan</enCityName><cnCityName>唐山</cnCityName><Abbreviation>TVS</Abbreviation></Address><Address diffgr:id="Address174" msdata:rowOrder="173"><enCityName>tengchong</enCityName><cnCityName>腾冲</cnCityName><Abbreviation>TCZ</Abbreviation></Address><Address diffgr:id="Address175" msdata:rowOrder="174"><enCityName>Tianjin</enCityName><cnCityName>天津</cnCityName><Abbreviation>TSN</Abbreviation></Address><Address diffgr:id="Address176" msdata:rowOrder="175"><enCityName>Tianshui</enCityName><cnCityName>天水</cnCityName><Abbreviation>THQ</Abbreviation></Address><Address diffgr:id="Address177" msdata:rowOrder="176"><enCityName>Tonghua</enCityName><cnCityName>通化</cnCityName><Abbreviation>TNH</Abbreviation></Address><Address diffgr:id="Address178" msdata:rowOrder="177"><enCityName>Tongliao</enCityName><cnCityName>通辽</cnCityName><Abbreviation>TGO</Abbreviation></Address><Address diffgr:id="Address179" msdata:rowOrder="178"><enCityName>Tongren</enCityName><cnCityName>铜仁市</cnCityName><Abbreviation>TEN</Abbreviation></Address><Address diffgr:id="Address180" msdata:rowOrder="179"><enCityName>tongren</enCityName><cnCityName>铜仁</cnCityName><Abbreviation>TEN</Abbreviation></Address><Address diffgr:id="Address181" msdata:rowOrder="180"><enCityName>tulufan</enCityName><cnCityName>吐鲁番</cnCityName><Abbreviation>TLQ</Abbreviation></Address><Address diffgr:id="Address182" msdata:rowOrder="181"><enCityName>WANZHOU</enCityName><cnCityName>万州</cnCityName><Abbreviation>WXN</Abbreviation></Address><Address diffgr:id="Address183" msdata:rowOrder="182"><enCityName>Weifang</enCityName><cnCityName>潍坊</cnCityName><Abbreviation>WEF</Abbreviation></Address><Address diffgr:id="Address184" msdata:rowOrder="183"><enCityName>Weihai</enCityName><cnCityName>威海</cnCityName><Abbreviation>WEH</Abbreviation></Address><Address diffgr:id="Address185" msdata:rowOrder="184"><enCityName>Wenshan</enCityName><cnCityName>文山县</cnCityName><Abbreviation>WNH</Abbreviation></Address><Address diffgr:id="Address186" msdata:rowOrder="185"><enCityName>wenshan</enCityName><cnCityName>文山</cnCityName><Abbreviation>WNH</Abbreviation></Address><Address diffgr:id="Address187" msdata:rowOrder="186"><enCityName>Wenzhou</enCityName><cnCityName>温州</cnCityName><Abbreviation>WNZ</Abbreviation></Address><Address diffgr:id="Address188" msdata:rowOrder="187"><enCityName>Wuhai</enCityName><cnCityName>乌海</cnCityName><Abbreviation>WUA</Abbreviation></Address><Address diffgr:id="Address189" msdata:rowOrder="188"><enCityName>Wuhan</enCityName><cnCityName>武汉</cnCityName><Abbreviation>WUH</Abbreviation></Address><Address diffgr:id="Address190" msdata:rowOrder="189"><enCityName>Wuhu</enCityName><cnCityName>芜湖</cnCityName><Abbreviation>WHU</Abbreviation></Address><Address diffgr:id="Address191" msdata:rowOrder="190"><enCityName>Wulanhaote</enCityName><cnCityName>乌兰浩特</cnCityName><Abbreviation>HLH</Abbreviation></Address><Address diffgr:id="Address192" msdata:rowOrder="191"><enCityName>Wulumuqi</enCityName><cnCityName>乌鲁木齐</cnCityName><Abbreviation>URC</Abbreviation></Address><Address diffgr:id="Address193" msdata:rowOrder="192"><enCityName>Wuxi</enCityName><cnCityName>无锡</cnCityName><Abbreviation>WUX</Abbreviation></Address><Address diffgr:id="Address194" msdata:rowOrder="193"><enCityName>Wuyishan</enCityName><cnCityName>武夷山</cnCityName><Abbreviation>WUS</Abbreviation></Address><Address diffgr:id="Address195" msdata:rowOrder="194"><enCityName>Wuzhou</enCityName><cnCityName>梧州</cnCityName><Abbreviation>WUZ</Abbreviation></Address><Address diffgr:id="Address196" msdata:rowOrder="195"><enCityName>Xiamen</enCityName><cnCityName>厦门</cnCityName><Abbreviation>XMN</Abbreviation></Address><Address diffgr:id="Address197" msdata:rowOrder="196"><enCityName>Xian</enCityName><cnCityName>西安</cnCityName><Abbreviation>SIA</Abbreviation></Address><Address diffgr:id="Address198" msdata:rowOrder="197"><enCityName>Xiangfan</enCityName><cnCityName>襄樊</cnCityName><Abbreviation>XFN</Abbreviation></Address><Address diffgr:id="Address199" msdata:rowOrder="198"><enCityName>Xianggelila</enCityName><cnCityName>香格里拉</cnCityName><Abbreviation>DIG</Abbreviation></Address><Address diffgr:id="Address200" msdata:rowOrder="199"><enCityName>Xiangyang</enCityName><cnCityName>襄阳</cnCityName><Abbreviation>XFN</Abbreviation></Address><Address diffgr:id="Address201" msdata:rowOrder="200"><enCityName>Xichang</enCityName><cnCityName>西昌</cnCityName><Abbreviation>XIC</Abbreviation></Address><Address diffgr:id="Address202" msdata:rowOrder="201"><enCityName>Xilinhaote</enCityName><cnCityName>锡林浩特</cnCityName><Abbreviation>XIL</Abbreviation></Address><Address diffgr:id="Address203" msdata:rowOrder="202"><enCityName>Xingtai</enCityName><cnCityName>邢台</cnCityName><Abbreviation>XNT</Abbreviation></Address><Address diffgr:id="Address204" msdata:rowOrder="203"><enCityName>Xingyi</enCityName><cnCityName>兴义</cnCityName><Abbreviation>ACX</Abbreviation></Address><Address diffgr:id="Address205" msdata:rowOrder="204"><enCityName>Xining</enCityName><cnCityName>西宁</cnCityName><Abbreviation>XNN</Abbreviation></Address><Address diffgr:id="Address206" msdata:rowOrder="205"><enCityName>Xishuangbanna</enCityName><cnCityName>西双版纳</cnCityName><Abbreviation>JHG</Abbreviation></Address><Address diffgr:id="Address207" msdata:rowOrder="206"><enCityName>Xuzhou</enCityName><cnCityName>徐州</cnCityName><Abbreviation>XUZ</Abbreviation></Address><Address diffgr:id="Address208" msdata:rowOrder="207"><enCityName>Yan'an</enCityName><cnCityName>延安</cnCityName><Abbreviation>ENY</Abbreviation></Address><Address diffgr:id="Address209" msdata:rowOrder="208"><enCityName>Yancheng</enCityName><cnCityName>盐城</cnCityName><Abbreviation>YNZ</Abbreviation></Address><Address diffgr:id="Address210" msdata:rowOrder="209"><enCityName>Yangzhou</enCityName><cnCityName>扬州</cnCityName><Abbreviation>YTY</Abbreviation></Address><Address diffgr:id="Address211" msdata:rowOrder="210"><enCityName>Yanji</enCityName><cnCityName>延吉</cnCityName><Abbreviation>YNJ</Abbreviation></Address><Address diffgr:id="Address212" msdata:rowOrder="211"><enCityName>Yantai</enCityName><cnCityName>烟台</cnCityName><Abbreviation>YNT</Abbreviation></Address><Address diffgr:id="Address213" msdata:rowOrder="212"><enCityName>Yibin</enCityName><cnCityName>宜宾</cnCityName><Abbreviation>YBP</Abbreviation></Address><Address diffgr:id="Address214" msdata:rowOrder="213"><enCityName>Yichang</enCityName><cnCityName>宜昌</cnCityName><Abbreviation>YIH</Abbreviation></Address><Address diffgr:id="Address215" msdata:rowOrder="214"><enCityName>Yichun</enCityName><cnCityName>宜春</cnCityName><Abbreviation>YIC</Abbreviation></Address><Address diffgr:id="Address216" msdata:rowOrder="215"><enCityName>Yichun</enCityName><cnCityName>伊春</cnCityName><Abbreviation>LDS</Abbreviation></Address><Address diffgr:id="Address217" msdata:rowOrder="216"><enCityName>Yili</enCityName><cnCityName>伊犁</cnCityName><Abbreviation>YIN</Abbreviation></Address><Address diffgr:id="Address218" msdata:rowOrder="217"><enCityName>Yinchuan</enCityName><cnCityName>银川</cnCityName><Abbreviation>INC</Abbreviation></Address><Address diffgr:id="Address219" msdata:rowOrder="218"><enCityName>Yining</enCityName><cnCityName>伊宁市</cnCityName><Abbreviation>YIN</Abbreviation></Address><Address diffgr:id="Address220" msdata:rowOrder="219"><enCityName>Yiwu</enCityName><cnCityName>义乌</cnCityName><Abbreviation>YIW</Abbreviation></Address><Address diffgr:id="Address221" msdata:rowOrder="220"><enCityName>Yongzhou</enCityName><cnCityName>永州</cnCityName><Abbreviation>LLF</Abbreviation></Address><Address diffgr:id="Address222" msdata:rowOrder="221"><enCityName>Yulin</enCityName><cnCityName>榆林</cnCityName><Abbreviation>UYN</Abbreviation></Address><Address diffgr:id="Address223" msdata:rowOrder="222"><enCityName>Yuncheng</enCityName><cnCityName>运城</cnCityName><Abbreviation>YCU</Abbreviation></Address><Address diffgr:id="Address224" msdata:rowOrder="223"><enCityName>yushu</enCityName><cnCityName>玉树</cnCityName><Abbreviation>YUS</Abbreviation></Address><Address diffgr:id="Address225" msdata:rowOrder="224"><enCityName>yushu</enCityName><cnCityName>玉树县</cnCityName><Abbreviation>YUS</Abbreviation></Address><Address diffgr:id="Address226" msdata:rowOrder="225"><enCityName>Zhangjiajie</enCityName><cnCityName>张家界</cnCityName><Abbreviation>DYG</Abbreviation></Address><Address diffgr:id="Address227" msdata:rowOrder="226"><enCityName>Zhangjiakou</enCityName><cnCityName>张家口</cnCityName><Abbreviation>ZQZ</Abbreviation></Address><Address diffgr:id="Address228" msdata:rowOrder="227"><enCityName>Zhangye</enCityName><cnCityName>张掖</cnCityName><Abbreviation>YZY</Abbreviation></Address><Address diffgr:id="Address229" msdata:rowOrder="228"><enCityName>Zhanjiang</enCityName><cnCityName>湛江</cnCityName><Abbreviation>ZHA</Abbreviation></Address><Address diffgr:id="Address230" msdata:rowOrder="229"><enCityName>Zhaotong</enCityName><cnCityName>昭通</cnCityName><Abbreviation>ZAT</Abbreviation></Address><Address diffgr:id="Address231" msdata:rowOrder="230"><enCityName>Zhengzhou</enCityName><cnCityName>郑州</cnCityName><Abbreviation>CGO</Abbreviation></Address><Address diffgr:id="Address232" msdata:rowOrder="231"><enCityName>zhijiang</enCityName><cnCityName>芷江</cnCityName><Abbreviation>HJJ</Abbreviation></Address><Address diffgr:id="Address233" msdata:rowOrder="232"><enCityName>Zhongshan</enCityName><cnCityName>中山</cnCityName><Abbreviation>ZGN</Abbreviation></Address><Address diffgr:id="Address234" msdata:rowOrder="233"><enCityName>Zhongwei</enCityName><cnCityName>中卫</cnCityName><Abbreviation>ZHY</Abbreviation></Address><Address diffgr:id="Address235" msdata:rowOrder="234"><enCityName>Zhoushan</enCityName><cnCityName>舟山</cnCityName><Abbreviation>HSN</Abbreviation></Address><Address diffgr:id="Address236" msdata:rowOrder="235"><enCityName>Zhuhai</enCityName><cnCityName>珠海</cnCityName><Abbreviation>ZUH</Abbreviation></Address><Address diffgr:id="Address237" msdata:rowOrder="236"><enCityName>Zhuzhou</enCityName><cnCityName>株洲</cnCityName><Abbreviation>ZUZ</Abbreviation></Address><Address diffgr:id="Address238" msdata:rowOrder="237"><enCityName>Zunyi</enCityName><cnCityName>遵义</cnCityName><Abbreviation>ZYI</Abbreviation></Address></Airline1></diffgr:diffgram></getDomesticCityResult></getDomesticCityResponse></soap:Body></soap:Envelope>